previewlink/__init__.py
previewlink/exceptions.py
previewlink/helper_utils.py
previewlink/preview.py
previewlink/source.py
previewlink-0.0.1.dist-info/LICENSE
previewlink-0.0.1.dist-info/METADATA
previewlink-0.0.1.dist-info/WHEEL
previewlink-0.0.1.dist-info/top_level.txt
previewlink-0.0.1.dist-info/RECORD
