Metadata-Version: 2.1
Name: previewlink
Version: 0.0.1
Summary: Get the preview of a website
Home-page: https://github.com/sreehari1997/link-preview/
Author: SREEHARI K V
Author-email: sreeharivijayan619@gmail.com
License: UNKNOWN
Project-URL: Bug Tracker, https://github.com/sreehari1997/link-preview/issues
Keywords: link preview,preview link,preview url
Platform: UNKNOWN
Classifier: Programming Language :: Python :: 3
Classifier: Programming Language :: Python :: 3.6
Classifier: Programming Language :: Python :: 3.7
Classifier: Programming Language :: Python :: 3.8
Classifier: Programming Language :: Python :: 3.9
Classifier: Programming Language :: Python :: 3 :: Only
Classifier: License :: OSI Approved :: MIT License
Classifier: Operating System :: OS Independent
Requires-Python: >=3.6
License-File: LICENSE
Requires-Dist: requests (>=2.22.0)
Requires-Dist: beautifulsoup4 (>=4.4.0)
Provides-Extra: dev
Requires-Dist: pytest-cov (==2.12.1) ; extra == 'dev'
Requires-Dist: pytest (==6.2.5) ; extra == 'dev'
Requires-Dist: pytest-httpserver (==1.0.1) ; extra == 'dev'
